rpa_sap/SapGui.py
rpa_sap/__init__.py
rpa_sap/lib/GridView.py
rpa_sap/lib/GuiTableControl.py
rpa_sap/lib/SQ01.py
rpa_sap/lib/__init__.py
rpa_sap/lib/common.py
rpa_sap-1.2.5.dist-info/licenses/LICENSE
rpa_sap-1.2.5.dist-info/METADATA
rpa_sap-1.2.5.dist-info/WHEEL
rpa_sap-1.2.5.dist-info/top_level.txt
rpa_sap-1.2.5.dist-info/RECORD
