Metadata-Version: 2.4
Name: rpa-sap
Version: 1.2.5
Summary: SAPGUI scripting automation
Requires-Python: >=3.10
License-File: LICENSE
Requires-Dist: openpyxl>=3.1.5
Requires-Dist: pandas>=2.3.3
Requires-Dist: pywin32>=311
Requires-Dist: wmi>=1.5.1
Dynamic: license-file
